{
  "schema_version": 2,
  "project_id": "scrubid_iclr_pack_v1_0_3",
  "project_version": "1.0.3",
  "run_key": "48003a0f8e8ccbb2c8ec1ad8867f35a9f96c19690c52c576b9215c5e39e28d32",
  "run_id": "run_20260118T175702Z_0069",
  "suite_id": "SUITE_SYNTH_V1",
  "experiment_id": "EXP_SYNTH_REDUNDANCY_SWEEP_V1",
  "intervention_family_id": "I_PATHPATCH",
  "candidate_generator_id": "G_MANUAL_SEED",
  "component_granularity": "node",
  "reference_distribution_id": "REFDIST_SYNTH_PAIRED_V1",
  "reference_assignment_id": "REFASSIGN_DERANGEMENT_SHUFFLE_V1",
  "timestamp_utc": "2026-01-18T17:57:02Z",
  "git_commit": "0000000000000000000000000000000000000000",
  "python_version": "3.12.10",
  "platform": "Windows-11-10.0.26200-SP0",
  "deterministic_mode": true,
  "seed_global": 1337,
  "seed_suite": 20260116,
  "seed_reference_pairing": 3386816574,
  "dataset_fingerprint": "3ead4bb8e951ad90e95f55c5040f501437d3d355cb4fac4cd726d3e322dc4eac",
  "reference_dataset_fingerprint": "9aeb979e0aa30b14c7bcaa64c78654c00ad38882ec1432fff994aa2c7c6bbb53",
  "baseline_score_s0": 1.0,
  "epsilon": 0.1,
  "best_circuit_mdl": 2.0,
  "best_circuit_size": 2,
  "faithfulness_delta": 0.0,
  "RR": 0.6666666666666667,
  "RR_verdict": "FAIL",
  "SSS": 0.7333333333333333,
  "SSS_verdict": "WARN",
  "CC": 0.8,
  "CC_verdict": "FAIL",
  "overall_verdict": "FAIL",
  "quality_gates_passed": false,
  "paths": {
    "logs_dir": ".",
    "results_dir": ".",
    "diagnostics_file": "diagnostics.json",
    "certificate_file": "certificate.json"
  },
  "setting_id": "setting_INDUCTION_8_11",
  "template_id": "INDUCTION",
  "redundancy_factor": 8,
  "run_record_hash": "2907a0faab4700afada0cc956eb70d27c4e0babc502fe3b94cfd723f80a22d7a"
}
