{
  "schema_version": 3,
  "project_id": "scrubid_iclr_pack_v1_0_3",
  "project_version": "1.0.3",
  "run_key": "dd2e71173f0cd737a4f42a251ca74837b97b87309beca3e8d4214c1b2e2c3b10",
  "run_id": "run_20260120T182317Z_0000",
  "suite_id": "SUITE_REAL_IOI_V1",
  "experiment_id": "EXP_REAL_IOI_V1",
  "model_id": "gpt2",
  "model_revision": "607a30d783dfa663caf39e06633721c8d4cfcd7e",
  "intervention_family_id": "I_ACTPATCH",
  "candidate_generator_id": "G_ATTR_PATCH",
  "component_granularity": "head_mlp",
  "reference_distribution_id": "REFDIST_IOI_CORRUPTED_V1",
  "reference_assignment_id": "REFASSIGN_INDEX_ALIGNED_V1",
  "timestamp_utc": "2026-01-20T18:28:42Z",
  "git_commit": "0000000000000000000000000000000000000000",
  "python_version": "3.12.10",
  "platform": "Windows-11-10.0.26200-SP0",
  "deterministic_mode": true,
  "seed_global": 1337,
  "seed_suite": 20260121,
  "seed_reference_pairing": 3086658242,
  "dataset_fingerprint": "4e831a5041f1692fb24bf3a1d1dc1fbfc7df63212e574e7106f184f4a99f1ab9",
  "reference_dataset_fingerprint": "05f5fd0eddee3fd90c385a1a1a3925722dbbf30fa1b1e84e0ed665545219a2d5",
  "baseline_score_s0": 3.949544967880086,
  "epsilon": 0.3949544967880086,
  "best_circuit_mdl": 124.0,
  "best_circuit_size": 124,
  "faithfulness_delta": 0.3191916488222698,
  "RR": 0.368421052631579,
  "RR_verdict": "WARN",
  "SSS": 0.6849664701032367,
  "SSS_verdict": "WARN",
  "CC": 0.09615384615384616,
  "CC_verdict": "PASS",
  "overall_verdict": "WARN",
  "quality_gates_passed": false,
  "paths": {
    "logs_dir": ".",
    "results_dir": ".",
    "diagnostics_file": "diagnostics.json"
  },
  "run_record_hash": "c9188823ad5a16e10be053b7268b07e92afc5c8ac1f0783828def59d95b6f328"
}
